{
  "preRequisiteTypes:7": [
    0,
    0,
    1
  ],
  "preRequisites:11": [
    312,
    299,
    678
  ],
  "properties:10": {
    "betterquesting:10": {
      "desc:8": "このエンジンはLVでも作ることができますが、生産する電力を使い切れる手段がない都合上、早くても電気高炉を作ったタイミングで建設することを推奨します。\n\nマルチブロックの組み立て方や動作原理については電気高炉のクエスト群を参照してください。\n\n産業用蒸気エンジンはGregicality Multiblocksが提供する最初のマルチブロックです。\n\nこのマルチブロックに要求されているダイナモハッチはエネルギーハッチの逆バージョンで、エネルギーを搬出します。\n\nこのエンジンにはMV以下のダイナモハッチしか取り付けられません。\nそれ以上の量の蒸気を電力に変換したい場合は大型蒸気タービンを利用しましょう。",
      "icon:10": {
        "Count:3": 1,
        "Damage:2": 2027,
        "id:8": "gregtech:machine"
      },
      "name:8": "GCYMにようこそ",
      "questlogic:8": "OR",
      "tasklogic:8": "OR"
    }
  },
  "questID:3": 317,
  "tasks:9": {
    "0:10": {
      "index:3": 0,
      "requiredItems:9": {
        "0:10": {
          "Count:3": 21,
          "Damage:2": 12,
          "id:8": "gcym:large_multiblock_casing"
        },
        "1:10": {
          "Count:3": 2,
          "id:8": "gregtech:turbine_casing"
        }
      },
      "taskID:8": "bq_standard:retrieval"
    },
    "1:10": {
      "index:3": 1,
      "requiredItems:9": {
        "0:10": {
          "Count:3": 1,
          "Damage:2": 2027,
          "id:8": "gregtech:machine"
        }
      },
      "taskID:8": "bq_standard:retrieval"
    },
    "2:10": {
      "entryLogic:8": "OR",
      "index:3": 2,
      "requiredItems:9": {
        "0:10": {
          "Count:3": 1,
          "Damage:2": 1226,
          "id:8": "gregtech:machine"
        },
        "1:10": {
          "Count:3": 1,
          "Damage:2": 1227,
          "id:8": "gregtech:machine"
        }
      },
      "taskID:8": "bq_standard:retrieval"
    }
  }
}