{
  "preRequisiteTypes:7": [
    0,
    1
  ],
  "preRequisites:11": [
    8,
    844
  ],
  "properties:10": {
    "betterquesting:10": {
      "desc:8": "初歩的なオーブンを建てると小麦からパンが焼けるようになります。\nマルチブロックの組み立て方はコークス炉のクエストを参照してください。\n\nまたスチーム機械版と電化版が要求されているように見えますが、説明上まとめただけなので安心してください。\n\n\n余談その1\nオーブンのUIに\"要メンテナンス\"が表示される不具合があったが修正された\n\n余談その2\nスチーム機械版はどこかのアップデートでスチーム消費量が削減し、使いやすくなりました。\nまた電化版は材料を入れると調理温度まで自動的に予熱し、調理完了すると予熱を止めてくれるようになりました。",
      "icon:10": {
        "Count:3": 1,
        "Damage:2": 8516,
        "id:8": "gregtech:machine"
      },
      "name:8": "脱リンゴ食",
      "questlogic:8": "OR"
    }
  },
  "questID:3": 6,
  "tasks:9": {
    "0:10": {
      "index:3": 0,
      "requiredItems:9": {
        "0:10": {
          "Count:3": 15,
          "id:8": "gregtechfoodoption:gtfo_casing"
        },
        "1:10": {
          "Count:3": 1,
          "Damage:2": 3,
          "id:8": "gregtech:meta_block_frame_3"
        }
      },
      "taskID:8": "bq_standard:retrieval"
    },
    "1:10": {
      "entryLogic:8": "OR",
      "index:3": 1,
      "requiredItems:9": {
        "0:10": {
          "Count:3": 1,
          "Damage:2": 8516,
          "id:8": "gregtech:machine"
        },
        "1:10": {
          "Count:3": 1,
          "Damage:2": 8544,
          "id:8": "gregtech:machine"
        },
        "2:10": {
          "Count:3": 1,
          "Damage:2": 8517,
          "id:8": "gregtech:machine"
        }
      },
      "taskID:8": "bq_standard:retrieval"
    }
  }
}