{
  "preRequisites:11": [
    334
  ],
  "properties:10": {
    "betterquesting:10": {
      "desc:8": "鉱石処理以外で\n遠心分離機は色んな物を色んな粉に分離したり、空気を分離したりと沢山の機能を持っています。\nとにかく遠心分離機は必須であることだけ認識しておけば大丈夫です。\n\n鉱石処理に関して\n遠心分離機は不純な粉と洗浄された粉を通常の粉に変換し、11.11%の確率で副産物を排出します。\nこれは最適な副産物の入手方法ではないですが、電力消費がとても小さいのでとりあえず動かしておくといいでしょう。\n\n\n余談その1\nGTCEではこの機械は簡単に使えて極小の粉を3つ出せたので最強の鉱石処理機械だった\nGTCEuでは鉱石処理の多様性を保つために性能が落とされた",
      "icon:10": {
        "Count:3": 1,
        "Damage:2": 185,
        "id:8": "gregtech:machine"
      },
      "name:8": "かつては溶岩とエンドストーンのために存在した"
    }
  },
  "questID:3": 380,
  "tasks:9": {
    "0:10": {
      "index:3": 0,
      "requiredItems:9": {
        "0:10": {
          "Count:3": 1,
          "Damage:2": 185,
          "id:8": "gregtech:machine"
        }
      },
      "taskID:8": "bq_standard:retrieval"
    }
  }
}