{
  "preRequisites:11": [
    92,
    110,
    82,
    74
  ],
  "properties:10": {
    "betterquesting:10": {
      "desc:8": "鉄はこのワールドに非常に潤沢に存在します。\nバニラと同じ名称の鉄鉱石としてだけでなく、色んな別の名前の酸化物鉱石として地中に埋まっています。\n\n今見ているクエストブックのページにてこのクエストと矢印で繋がっている4種類の鉱石を焼けばいずれも鉄になります。\n粉砕機の作成まで鉄を余り直接かまどで焼きたくないと思うかもしれませんが、鉄はとにかく大量に余る金属の筆頭なのでどんどん焼きましょう。",
      "icon:10": {
        "Count:3": 1,
        "id:8": "minecraft:iron_ingot"
      },
      "name:8": "鉄板(を作れる)アイテム",
      "questlogic:8": "OR"
    }
  },
  "questID:3": 81,
  "tasks:9": {
    "0:10": {
      "index:3": 0,
      "requiredItems:9": {
        "0:10": {
          "Count:3": 1,
          "id:8": "minecraft:iron_ingot"
        }
      },
      "taskID:8": "bq_standard:retrieval"
    }
  }
}